{
  "report_info": {
    "url": "https://uwu-logs.xyz/reports/25-08-21--19-51--Neth--Onyxia/",
    "scraped_at": "2025-08-21T19:57:45.054482",
    "date": "25-08-21",
    "time": "19-51",
    "player": "Neth",
    "encounter": "Onyxia"
  },
  "players": [
    {
      "rank": 1,
      "name": "Total",
      "total_damage": 98951897,
      "dps": 15157.0,
      "useful_damage": 15157.0,
      "total_heal": 17186157,
      "hps": 2632.5,
      "damage_taken": 0,
      "dtps": 0,
      "spell_resurrects": 0,
      "spell_mark_of_the_wild": 0,
      "spell_faerie_fire": 0,
      "spell_fortitude": 0,
      "spell_intellect": 0,
      "spell_demonicdark_rune": 0,
      "spell_interrupts": 0,
      "spell_drums": 0,
      "spell_dispels": 0,
      "spell_shouts": 0,
      "spell_feladabomb": 0,
      "spell_gift_of_the_wild": 0,
      "spell_power_word:_fortitude": 0,
      "spell_prayer_of_fortitude": 0,
      "spell_arcane_intellect": 0,
      "spell_arcane_brilliance": 0,
      "spell_thunder_clap": 0,
      "spell_sunder_armor": 0,
      "spell_demoralizing_shout": 0,
      "spell_pummel": 0,
      "spell_faerie_fire_feral": 0,
      "spell_insect_swarm": 0,
      "spell_innervate": 0,
      "spell_curse_of_the_elements": 0,
      "spell_curse_of_recklessness": 0,
      "spell_curse_of_tongues": 0,
      "spell_curse_of_agony": 0,
      "spell_curse_of_doom": 0,
      "spell_shadow_vulnerability": 0,
      "spell_mana_tide_totem": 0,
      "spell_natures_swiftness": 0,
      "spell_natures_swiftnessd": 0,
      "spell_ancestral_spirit": 0,
      "spell_resurrection": 0,
      "spell_redemption": 0,
      "spell_rebirth": 0,
      "spell_bloodlust": 0,
      "spell_purge": 0,
      "spell_scroll_of_strength": 0,
      "spell_scroll_of_agility": 0,
      "spell_elixir_of_demonslaying": 0,
      "spell_braided_eternium_chain": 0,
      "spell_chain_of_the_twilight_owl": 0,
      "spell_eye_of_the_night": 0,
      "spell_dark_rune": 0,
      "spell_demonic_rune": 0,
      "spell_earth_shock": 0,
      "spell_earth_shock_r1": 0,
      "spell_kick": 0,
      "spell_counterspell": 0,
      "spell_drums_of_war": 0,
      "spell_drums_of_battle": 0,
      "spell_drums_of_speed": 0,
      "spell_drums_of_restoration": 0,
      "spell_nightmare_seed": 0,
      "spell_annihilator": 0,
      "spell_arcane_bomb": 0,
      "spell_fel_iron_bomb": 0,
      "spell_adamantite_grenade": 0,
      "spell_mass_dispel": 0,
      "spell_dispel_magic": 0,
      "spell_abolish_disease": 0,
      "spell_cleanse": 0,
      "spell_remove_lesser_curse": 0,
      "spell_spellsteal": 0,
      "spell_poison_cleansing_totem": 0,
      "spell_cure_poison": 0,
      "spell_cure_disease": 0,
      "spell_remove_curse": 0,
      "spell_abolish_poison": 0,
      "spell_shield_slam": 0,
      "spell_tranquilizing_shot": 0,
      "spell_commanding_shout": 0,
      "spell_battle_shout": 0,
      "spell_misdirection": 0,
      "mana_potion": 0
    },
    {
      "rank": 2,
      "name": "Zcope",
      "total_damage": 8178478,
      "dps": 1252.7,
      "useful_damage": 1252.7,
      "total_heal": 106425,
      "hps": 16.3,
      "damage_taken": 0,
      "dtps": 0,
      "haste_potion": 7,
      "destruction_potion": 0,
      "goblin_sapper_charge": 1,
      "super_sapper_charge": 1,
      "spell_resurrects": 0,
      "spell_mark_of_the_wild": 0,
      "spell_faerie_fire": 0,
      "spell_fortitude": 0,
      "spell_intellect": 0,
      "spell_demonicdark_rune": 3,
      "spell_interrupts": 0,
      "spell_drums": 11,
      "spell_dispels": 0,
      "spell_shouts": 0,
      "spell_feladabomb": 0,
      "spell_gift_of_the_wild": 0,
      "spell_power_word:_fortitude": 0,
      "spell_prayer_of_fortitude": 0,
      "spell_arcane_intellect": 0,
      "spell_arcane_brilliance": 0,
      "spell_thunder_clap": 0,
      "spell_sunder_armor": 0,
      "spell_demoralizing_shout": 0,
      "spell_pummel": 0,
      "spell_faerie_fire_feral": 0,
      "spell_insect_swarm": 0,
      "spell_innervate": 0,
      "spell_curse_of_the_elements": 0,
      "spell_curse_of_recklessness": 0,
      "spell_curse_of_tongues": 0,
      "spell_curse_of_agony": 0,
      "spell_curse_of_doom": 0,
      "spell_shadow_vulnerability": 0,
      "spell_mana_tide_totem": 0,
      "spell_natures_swiftness": 0,
      "spell_natures_swiftnessd": 0,
      "spell_ancestral_spirit": 0,
      "spell_resurrection": 0,
      "spell_redemption": 0,
      "spell_rebirth": 0,
      "spell_bloodlust": 0,
      "spell_purge": 0,
      "spell_scroll_of_strength": 5,
      "spell_scroll_of_agility": 5,
      "spell_elixir_of_demonslaying": 4,
      "spell_braided_eternium_chain": 0,
      "spell_chain_of_the_twilight_owl": 0,
      "spell_eye_of_the_night": 0,
      "spell_dark_rune": 3,
      "spell_demonic_rune": 0,
      "spell_earth_shock": 0,
      "spell_earth_shock_r1": 0,
      "spell_kick": 0,
      "spell_counterspell": 0,
      "spell_drums_of_war": 2,
      "spell_drums_of_battle": 9,
      "spell_drums_of_speed": 0,
      "spell_drums_of_restoration": 0,
      "spell_nightmare_seed": 2,
      "spell_annihilator": 0,
      "spell_arcane_bomb": 0,
      "spell_fel_iron_bomb": 0,
      "spell_adamantite_grenade": 0,
      "spell_mass_dispel": 0,
      "spell_dispel_magic": 0,
      "spell_abolish_disease": 0,
      "spell_cleanse": 0,
      "spell_remove_lesser_curse": 0,
      "spell_spellsteal": 0,
      "spell_poison_cleansing_totem": 0,
      "spell_cure_poison": 0,
      "spell_cure_disease": 0,
      "spell_remove_curse": 0,
      "spell_abolish_poison": 0,
      "spell_shield_slam": 0,
      "spell_tranquilizing_shot": 0,
      "spell_commanding_shout": 0,
      "spell_battle_shout": 0,
      "spell_misdirection": 19,
      "mana_potion": 7
    },
    {
      "rank": 3,
      "name": "Neth",
      "total_damage": 7423219,
      "dps": 1137.0,
      "useful_damage": 1137.0,
      "total_heal": 114230,
      "hps": 17.4,
      "damage_taken": 0,
      "dtps": 0,
      "haste_potion": 17,
      "destruction_potion": 0,
      "goblin_sapper_charge": 9,
      "super_sapper_charge": 12,
      "spell_resurrects": 0,
      "spell_mark_of_the_wild": 0,
      "spell_faerie_fire": 0,
      "spell_fortitude": 0,
      "spell_intellect": 0,
      "spell_demonicdark_rune": 0,
      "spell_interrupts": 7,
      "spell_drums": 0,
      "spell_dispels": 0,
      "spell_shouts": 57,
      "spell_feladabomb": 0,
      "spell_gift_of_the_wild": 0,
      "spell_power_word:_fortitude": 0,
      "spell_prayer_of_fortitude": 0,
      "spell_arcane_intellect": 0,
      "spell_arcane_brilliance": 0,
      "spell_thunder_clap": 0,
      "spell_sunder_armor": 171,
      "spell_demoralizing_shout": 4,
      "spell_pummel": 7,
      "spell_faerie_fire_feral": 0,
      "spell_insect_swarm": 0,
      "spell_innervate": 0,
      "spell_curse_of_the_elements": 0,
      "spell_curse_of_recklessness": 0,
      "spell_curse_of_tongues": 0,
      "spell_curse_of_agony": 0,
      "spell_curse_of_doom": 0,
      "spell_shadow_vulnerability": 0,
      "spell_mana_tide_totem": 0,
      "spell_natures_swiftness": 0,
      "spell_natures_swiftnessd": 0,
      "spell_ancestral_spirit": 0,
      "spell_resurrection": 0,
      "spell_redemption": 0,
      "spell_rebirth": 0,
      "spell_bloodlust": 0,
      "spell_purge": 0,
      "spell_scroll_of_strength": 6,
      "spell_scroll_of_agility": 6,
      "spell_elixir_of_demonslaying": 5,
      "spell_braided_eternium_chain": 1,
      "spell_chain_of_the_twilight_owl": 0,
      "spell_eye_of_the_night": 0,
      "spell_dark_rune": 0,
      "spell_demonic_rune": 0,
      "spell_earth_shock": 0,
      "spell_earth_shock_r1": 0,
      "spell_kick": 0,
      "spell_counterspell": 0,
      "spell_drums_of_war": 0,
      "spell_drums_of_battle": 0,
      "spell_drums_of_speed": 0,
      "spell_drums_of_restoration": 0,
      "spell_nightmare_seed": 5,
      "spell_annihilator": 0,
      "spell_arcane_bomb": 0,
      "spell_fel_iron_bomb": 0,
      "spell_adamantite_grenade": 0,
      "spell_mass_dispel": 0,
      "spell_dispel_magic": 0,
      "spell_abolish_disease": 0,
      "spell_cleanse": 0,
      "spell_remove_lesser_curse": 0,
      "spell_spellsteal": 0,
      "spell_poison_cleansing_totem": 0,
      "spell_cure_poison": 0,
      "spell_cure_disease": 0,
      "spell_remove_curse": 0,
      "spell_abolish_poison": 0,
      "spell_shield_slam": 0,
      "spell_tranquilizing_shot": 0,
      "spell_commanding_shout": 0,
      "spell_battle_shout": 57,
      "spell_misdirection": 0,
      "mana_potion": 0
    },
    {
      "rank": 4,
      "name": "Onlakw",
      "total_damage": 6997017,
      "dps": 1071.7,
      "useful_damage": 1071.7,
      "total_heal": 13928,
      "hps": 2.1,
      "damage_taken": 0,
      "dtps": 0,
      "haste_potion": 0,
      "destruction_potion": 12,
      "goblin_sapper_charge": 0,
      "super_sapper_charge": 0,
      "spell_resurrects": 0,
      "spell_mark_of_the_wild": 0,
      "spell_faerie_fire": 0,
      "spell_fortitude": 0,
      "spell_intellect": 0,
      "spell_demonicdark_rune": 3,
      "spell_interrupts": 0,
      "spell_drums": 18,
      "spell_dispels": 0,
      "spell_shouts": 0,
      "spell_feladabomb": 0,
      "spell_gift_of_the_wild": 0,
      "spell_power_word:_fortitude": 0,
      "spell_prayer_of_fortitude": 0,
      "spell_arcane_intellect": 0,
      "spell_arcane_brilliance": 0,
      "spell_thunder_clap": 0,
      "spell_sunder_armor": 0,
      "spell_demoralizing_shout": 0,
      "spell_pummel": 0,
      "spell_faerie_fire_feral": 0,
      "spell_insect_swarm": 0,
      "spell_innervate": 0,
      "spell_curse_of_the_elements": 0,
      "spell_curse_of_recklessness": 0,
      "spell_curse_of_tongues": 9,
      "spell_curse_of_agony": 132,
      "spell_curse_of_doom": 16,
      "spell_shadow_vulnerability": 304,
      "spell_mana_tide_totem": 0,
      "spell_natures_swiftness": 0,
      "spell_natures_swiftnessd": 0,
      "spell_ancestral_spirit": 0,
      "spell_resurrection": 0,
      "spell_redemption": 0,
      "spell_rebirth": 0,
      "spell_bloodlust": 0,
      "spell_purge": 0,
      "spell_scroll_of_strength": 1,
      "spell_scroll_of_agility": 1,
      "spell_elixir_of_demonslaying": 0,
      "spell_braided_eternium_chain": 0,
      "spell_chain_of_the_twilight_owl": 0,
      "spell_eye_of_the_night": 1,
      "spell_dark_rune": 3,
      "spell_demonic_rune": 0,
      "spell_earth_shock": 0,
      "spell_earth_shock_r1": 0,
      "spell_kick": 0,
      "spell_counterspell": 0,
      "spell_drums_of_war": 0,
      "spell_drums_of_battle": 18,
      "spell_drums_of_speed": 0,
      "spell_drums_of_restoration": 0,
      "spell_nightmare_seed": 2,
      "spell_annihilator": 0,
      "spell_arcane_bomb": 0,
      "spell_fel_iron_bomb": 0,
      "spell_adamantite_grenade": 0,
      "spell_mass_dispel": 0,
      "spell_dispel_magic": 0,
      "spell_abolish_disease": 0,
      "spell_cleanse": 0,
      "spell_remove_lesser_curse": 0,
      "spell_spellsteal": 0,
      "spell_poison_cleansing_totem": 0,
      "spell_cure_poison": 0,
      "spell_cure_disease": 0,
      "spell_remove_curse": 0,
      "spell_abolish_poison": 0,
      "spell_shield_slam": 0,
      "spell_tranquilizing_shot": 0,
      "spell_commanding_shout": 0,
      "spell_battle_shout": 0,
      "spell_misdirection": 0,
      "mana_potion": 0
    },
    {
      "rank": 5,
      "name": "Littlerabbit",
      "total_damage": 6561174,
      "dps": 1005.0,
      "useful_damage": 1005.0,
      "total_heal": 81726,
      "hps": 12.5,
      "damage_taken": 0,
      "dtps": 0,
      "haste_potion": 10,
      "destruction_potion": 0,
      "goblin_sapper_charge": 0,
      "super_sapper_charge": 0,
      "spell_resurrects": 0,
      "spell_mark_of_the_wild": 0,
      "spell_faerie_fire": 0,
      "spell_fortitude": 0,
      "spell_intellect": 0,
      "spell_demonicdark_rune": 5,
      "spell_interrupts": 0,
      "spell_drums": 8,
      "spell_dispels": 3,
      "spell_shouts": 0,
      "spell_feladabomb": 0,
      "spell_gift_of_the_wild": 0,
      "spell_power_word:_fortitude": 0,
      "spell_prayer_of_fortitude": 0,
      "spell_arcane_intellect": 0,
      "spell_arcane_brilliance": 0,
      "spell_thunder_clap": 0,
      "spell_sunder_armor": 0,
      "spell_demoralizing_shout": 0,
      "spell_pummel": 0,
      "spell_faerie_fire_feral": 0,
      "spell_insect_swarm": 0,
      "spell_innervate": 0,
      "spell_curse_of_the_elements": 0,
      "spell_curse_of_recklessness": 0,
      "spell_curse_of_tongues": 0,
      "spell_curse_of_agony": 0,
      "spell_curse_of_doom": 0,
      "spell_shadow_vulnerability": 0,
      "spell_mana_tide_totem": 0,
      "spell_natures_swiftness": 0,
      "spell_natures_swiftnessd": 0,
      "spell_ancestral_spirit": 0,
      "spell_resurrection": 0,
      "spell_redemption": 0,
      "spell_rebirth": 0,
      "spell_bloodlust": 0,
      "spell_purge": 0,
      "spell_scroll_of_strength": 6,
      "spell_scroll_of_agility": 9,
      "spell_elixir_of_demonslaying": 5,
      "spell_braided_eternium_chain": 2,
      "spell_chain_of_the_twilight_owl": 0,
      "spell_eye_of_the_night": 0,
      "spell_dark_rune": 5,
      "spell_demonic_rune": 0,
      "spell_earth_shock": 0,
      "spell_earth_shock_r1": 0,
      "spell_kick": 0,
      "spell_counterspell": 0,
      "spell_drums_of_war": 2,
      "spell_drums_of_battle": 6,
      "spell_drums_of_speed": 0,
      "spell_drums_of_restoration": 0,
      "spell_nightmare_seed": 1,
      "spell_annihilator": 0,
      "spell_arcane_bomb": 0,
      "spell_fel_iron_bomb": 0,
      "spell_adamantite_grenade": 0,
      "spell_mass_dispel": 0,
      "spell_dispel_magic": 0,
      "spell_abolish_disease": 0,
      "spell_cleanse": 0,
      "spell_remove_lesser_curse": 0,
      "spell_spellsteal": 0,
      "spell_poison_cleansing_totem": 0,
      "spell_cure_poison": 0,
      "spell_cure_disease": 0,
      "spell_remove_curse": 0,
      "spell_abolish_poison": 0,
      "spell_shield_slam": 0,
      "spell_tranquilizing_shot": 3,
      "spell_commanding_shout": 0,
      "spell_battle_shout": 0,
      "spell_misdirection": 17,
      "mana_potion": 4
    },
    {
      "rank": 6,
      "name": "Ldn",
      "total_damage": 6024065,
      "dps": 922.7,
      "useful_damage": 922.7,
      "total_heal": 75539,
      "hps": 11.5,
      "damage_taken": 0,
      "dtps": 0,
      "haste_potion": 0,
      "destruction_potion": 12,
      "goblin_sapper_charge": 1,
      "super_sapper_charge": 0,
      "spell_resurrects": 0,
      "spell_mark_of_the_wild": 0,
      "spell_faerie_fire": 0,
      "spell_fortitude": 0,
      "spell_intellect": 0,
      "spell_demonicdark_rune": 1,
      "spell_interrupts": 0,
      "spell_drums": 11,
      "spell_dispels": 0,
      "spell_shouts": 0,
      "spell_feladabomb": 0,
      "spell_gift_of_the_wild": 0,
      "spell_power_word:_fortitude": 0,
      "spell_prayer_of_fortitude": 0,
      "spell_arcane_intellect": 0,
      "spell_arcane_brilliance": 0,
      "spell_thunder_clap": 0,
      "spell_sunder_armor": 0,
      "spell_demoralizing_shout": 0,
      "spell_pummel": 0,
      "spell_faerie_fire_feral": 0,
      "spell_insect_swarm": 0,
      "spell_innervate": 0,
      "spell_curse_of_the_elements": 1,
      "spell_curse_of_recklessness": 93,
      "spell_curse_of_tongues": 11,
      "spell_curse_of_agony": 13,
      "spell_curse_of_doom": 4,
      "spell_shadow_vulnerability": 270,
      "spell_mana_tide_totem": 0,
      "spell_natures_swiftness": 0,
      "spell_natures_swiftnessd": 0,
      "spell_ancestral_spirit": 0,
      "spell_resurrection": 0,
      "spell_redemption": 0,
      "spell_rebirth": 0,
      "spell_bloodlust": 0,
      "spell_purge": 0,
      "spell_scroll_of_strength": 0,
      "spell_scroll_of_agility": 0,
      "spell_elixir_of_demonslaying": 0,
      "spell_braided_eternium_chain": 0,
      "spell_chain_of_the_twilight_owl": 2,
      "spell_eye_of_the_night": 0,
      "spell_dark_rune": 1,
      "spell_demonic_rune": 0,
      "spell_earth_shock": 0,
      "spell_earth_shock_r1": 0,
      "spell_kick": 0,
      "spell_counterspell": 0,
      "spell_drums_of_war": 0,
      "spell_drums_of_battle": 11,
      "spell_drums_of_speed": 0,
      "spell_drums_of_restoration": 0,
      "spell_nightmare_seed": 2,
      "spell_annihilator": 0,
      "spell_arcane_bomb": 0,
      "spell_fel_iron_bomb": 0,
      "spell_adamantite_grenade": 0,
      "spell_mass_dispel": 0,
      "spell_dispel_magic": 0,
      "spell_abolish_disease": 0,
      "spell_cleanse": 0,
      "spell_remove_lesser_curse": 0,
      "spell_spellsteal": 0,
      "spell_poison_cleansing_totem": 0,
      "spell_cure_poison": 0,
      "spell_cure_disease": 0,
      "spell_remove_curse": 0,
      "spell_abolish_poison": 0,
      "spell_shield_slam": 0,
      "spell_tranquilizing_shot": 0,
      "spell_commanding_shout": 0,
      "spell_battle_shout": 0,
      "spell_misdirection": 0,
      "mana_potion": 0
    },
    {
      "rank": 7,
      "name": "Krixer",
      "total_damage": 5507901,
      "dps": 843.6,
      "useful_damage": 843.6,
      "total_heal": 22044,
      "hps": 3.3,
      "damage_taken": 0,
      "dtps": 0,
      "haste_potion": 13,
      "destruction_potion": 0,
      "goblin_sapper_charge": 0,
      "super_sapper_charge": 5,
      "spell_resurrects": 0,
      "spell_mark_of_the_wild": 0,
      "spell_faerie_fire": 0,
      "spell_fortitude": 0,
      "spell_intellect": 0,
      "spell_demonicdark_rune": 0,
      "spell_interrupts": 0,
      "spell_drums": 12,
      "spell_dispels": 0,
      "spell_shouts": 0,
      "spell_feladabomb": 0,
      "spell_gift_of_the_wild": 0,
      "spell_power_word:_fortitude": 0,
      "spell_prayer_of_fortitude": 0,
      "spell_arcane_intellect": 0,
      "spell_arcane_brilliance": 0,
      "spell_thunder_clap": 0,
      "spell_sunder_armor": 0,
      "spell_demoralizing_shout": 0,
      "spell_pummel": 0,
      "spell_faerie_fire_feral": 0,
      "spell_insect_swarm": 0,
      "spell_innervate": 0,
      "spell_curse_of_the_elements": 0,
      "spell_curse_of_recklessness": 0,
      "spell_curse_of_tongues": 0,
      "spell_curse_of_agony": 0,
      "spell_curse_of_doom": 0,
      "spell_shadow_vulnerability": 0,
      "spell_mana_tide_totem": 0,
      "spell_natures_swiftness": 0,
      "spell_natures_swiftnessd": 0,
      "spell_ancestral_spirit": 0,
      "spell_resurrection": 0,
      "spell_redemption": 0,
      "spell_rebirth": 0,
      "spell_bloodlust": 0,
      "spell_purge": 0,
      "spell_scroll_of_strength": 9,
      "spell_scroll_of_agility": 9,
      "spell_elixir_of_demonslaying": 3,
      "spell_braided_eternium_chain": 0,
      "spell_chain_of_the_twilight_owl": 0,
      "spell_eye_of_the_night": 1,
      "spell_dark_rune": 0,
      "spell_demonic_rune": 0,
      "spell_earth_shock": 0,
      "spell_earth_shock_r1": 0,
      "spell_kick": 0,
      "spell_counterspell": 0,
      "spell_drums_of_war": 0,
      "spell_drums_of_battle": 12,
      "spell_drums_of_speed": 0,
      "spell_drums_of_restoration": 0,
      "spell_nightmare_seed": 2,
      "spell_annihilator": 0,
      "spell_arcane_bomb": 0,
      "spell_fel_iron_bomb": 0,
      "spell_adamantite_grenade": 0,
      "spell_mass_dispel": 0,
      "spell_dispel_magic": 0,
      "spell_abolish_disease": 0,
      "spell_cleanse": 0,
      "spell_remove_lesser_curse": 0,
      "spell_spellsteal": 0,
      "spell_poison_cleansing_totem": 0,
      "spell_cure_poison": 0,
      "spell_cure_disease": 0,
      "spell_remove_curse": 0,
      "spell_abolish_poison": 0,
      "spell_shield_slam": 0,
      "spell_tranquilizing_shot": 0,
      "spell_commanding_shout": 0,
      "spell_battle_shout": 0,
      "spell_misdirection": 12,
      "mana_potion": 0
    },
    {
      "rank": 8,
      "name": "Kasst",
      "total_damage": 5411912,
      "dps": 828.9,
      "useful_damage": 828.9,
      "total_heal": 91407,
      "hps": 14.0,
      "damage_taken": 0,
      "dtps": 0,
      "haste_potion": 2,
      "destruction_potion": 0,
      "goblin_sapper_charge": 0,
      "super_sapper_charge": 1,
      "spell_resurrects": 0,
      "spell_mark_of_the_wild": 0,
      "spell_faerie_fire": 0,
      "spell_fortitude": 0,
      "spell_intellect": 0,
      "spell_demonicdark_rune": 0,
      "spell_interrupts": 1,
      "spell_drums": 0,
      "spell_dispels": 0,
      "spell_shouts": 75,
      "spell_feladabomb": 4,
      "spell_gift_of_the_wild": 0,
      "spell_power_word:_fortitude": 0,
      "spell_prayer_of_fortitude": 0,
      "spell_arcane_intellect": 0,
      "spell_arcane_brilliance": 0,
      "spell_thunder_clap": 0,
      "spell_sunder_armor": 80,
      "spell_demoralizing_shout": 0,
      "spell_pummel": 1,
      "spell_faerie_fire_feral": 0,
      "spell_insect_swarm": 0,
      "spell_innervate": 0,
      "spell_curse_of_the_elements": 0,
      "spell_curse_of_recklessness": 0,
      "spell_curse_of_tongues": 0,
      "spell_curse_of_agony": 0,
      "spell_curse_of_doom": 0,
      "spell_shadow_vulnerability": 0,
      "spell_mana_tide_totem": 0,
      "spell_natures_swiftness": 0,
      "spell_natures_swiftnessd": 0,
      "spell_ancestral_spirit": 0,
      "spell_resurrection": 0,
      "spell_redemption": 0,
      "spell_rebirth": 0,
      "spell_bloodlust": 0,
      "spell_purge": 0,
      "spell_scroll_of_strength": 3,
      "spell_scroll_of_agility": 0,
      "spell_elixir_of_demonslaying": 4,
      "spell_braided_eternium_chain": 0,
      "spell_chain_of_the_twilight_owl": 0,
      "spell_eye_of_the_night": 0,
      "spell_dark_rune": 0,
      "spell_demonic_rune": 0,
      "spell_earth_shock": 0,
      "spell_earth_shock_r1": 0,
      "spell_kick": 0,
      "spell_counterspell": 0,
      "spell_drums_of_war": 0,
      "spell_drums_of_battle": 0,
      "spell_drums_of_speed": 0,
      "spell_drums_of_restoration": 0,
      "spell_nightmare_seed": 1,
      "spell_annihilator": 0,
      "spell_arcane_bomb": 0,
      "spell_fel_iron_bomb": 4,
      "spell_adamantite_grenade": 0,
      "spell_mass_dispel": 0,
      "spell_dispel_magic": 0,
      "spell_abolish_disease": 0,
      "spell_cleanse": 0,
      "spell_remove_lesser_curse": 0,
      "spell_spellsteal": 0,
      "spell_poison_cleansing_totem": 0,
      "spell_cure_poison": 0,
      "spell_cure_disease": 0,
      "spell_remove_curse": 0,
      "spell_abolish_poison": 0,
      "spell_shield_slam": 0,
      "spell_tranquilizing_shot": 0,
      "spell_commanding_shout": 0,
      "spell_battle_shout": 75,
      "spell_misdirection": 0,
      "mana_potion": 0
    },
    {
      "rank": 9,
      "name": "Mati",
      "total_damage": 5351432,
      "dps": 819.7,
      "useful_damage": 819.7,
      "total_heal": 6523,
      "hps": 0.9,
      "damage_taken": 0,
      "dtps": 0,
      "haste_potion": 0,
      "destruction_potion": 9,
      "goblin_sapper_charge": 0,
      "super_sapper_charge": 3,
      "spell_resurrects": 0,
      "spell_mark_of_the_wild": 0,
      "spell_faerie_fire": 0,
      "spell_fortitude": 0,
      "spell_intellect": 162,
      "spell_demonicdark_rune": 0,
      "spell_interrupts": 3,
      "spell_drums": 0,
      "spell_dispels": 42,
      "spell_shouts": 0,
      "spell_feladabomb": 0,
      "spell_gift_of_the_wild": 0,
      "spell_power_word:_fortitude": 0,
      "spell_prayer_of_fortitude": 0,
      "spell_arcane_intellect": 3,
      "spell_arcane_brilliance": 159,
      "spell_thunder_clap": 0,
      "spell_sunder_armor": 0,
      "spell_demoralizing_shout": 0,
      "spell_pummel": 0,
      "spell_faerie_fire_feral": 0,
      "spell_insect_swarm": 0,
      "spell_innervate": 0,
      "spell_curse_of_the_elements": 0,
      "spell_curse_of_recklessness": 0,
      "spell_curse_of_tongues": 0,
      "spell_curse_of_agony": 0,
      "spell_curse_of_doom": 0,
      "spell_shadow_vulnerability": 0,
      "spell_mana_tide_totem": 0,
      "spell_natures_swiftness": 0,
      "spell_natures_swiftnessd": 0,
      "spell_ancestral_spirit": 0,
      "spell_resurrection": 0,
      "spell_redemption": 0,
      "spell_rebirth": 0,
      "spell_bloodlust": 0,
      "spell_purge": 0,
      "spell_scroll_of_strength": 0,
      "spell_scroll_of_agility": 0,
      "spell_elixir_of_demonslaying": 0,
      "spell_braided_eternium_chain": 0,
      "spell_chain_of_the_twilight_owl": 0,
      "spell_eye_of_the_night": 0,
      "spell_dark_rune": 0,
      "spell_demonic_rune": 0,
      "spell_earth_shock": 0,
      "spell_earth_shock_r1": 0,
      "spell_kick": 0,
      "spell_counterspell": 3,
      "spell_drums_of_war": 0,
      "spell_drums_of_battle": 0,
      "spell_drums_of_speed": 0,
      "spell_drums_of_restoration": 0,
      "spell_nightmare_seed": 0,
      "spell_annihilator": 0,
      "spell_arcane_bomb": 0,
      "spell_fel_iron_bomb": 0,
      "spell_adamantite_grenade": 0,
      "spell_mass_dispel": 0,
      "spell_dispel_magic": 0,
      "spell_abolish_disease": 0,
      "spell_cleanse": 0,
      "spell_remove_lesser_curse": 33,
      "spell_spellsteal": 9,
      "spell_poison_cleansing_totem": 0,
      "spell_cure_poison": 0,
      "spell_cure_disease": 0,
      "spell_remove_curse": 0,
      "spell_abolish_poison": 0,
      "spell_shield_slam": 0,
      "spell_tranquilizing_shot": 0,
      "spell_commanding_shout": 0,
      "spell_battle_shout": 0,
      "spell_misdirection": 0,
      "mana_potion": 3
    },
    {
      "rank": 10,
      "name": "Yolohse",
      "total_damage": 5230361,
      "dps": 801.1,
      "useful_damage": 801.1,
      "total_heal": 84118,
      "hps": 12.8,
      "damage_taken": 0,
      "dtps": 0,
      "haste_potion": 0,
      "destruction_potion": 11,
      "goblin_sapper_charge": 0,
      "super_sapper_charge": 0,
      "spell_resurrects": 0,
      "spell_mark_of_the_wild": 0,
      "spell_faerie_fire": 0,
      "spell_fortitude": 0,
      "spell_intellect": 0,
      "spell_demonicdark_rune": 6,
      "spell_interrupts": 0,
      "spell_drums": 11,
      "spell_dispels": 0,
      "spell_shouts": 0,
      "spell_feladabomb": 0,
      "spell_gift_of_the_wild": 0,
      "spell_power_word:_fortitude": 0,
      "spell_prayer_of_fortitude": 0,
      "spell_arcane_intellect": 0,
      "spell_arcane_brilliance": 0,
      "spell_thunder_clap": 0,
      "spell_sunder_armor": 0,
      "spell_demoralizing_shout": 0,
      "spell_pummel": 0,
      "spell_faerie_fire_feral": 0,
      "spell_insect_swarm": 0,
      "spell_innervate": 0,
      "spell_curse_of_the_elements": 162,
      "spell_curse_of_recklessness": 0,
      "spell_curse_of_tongues": 0,
      "spell_curse_of_agony": 5,
      "spell_curse_of_doom": 4,
      "spell_shadow_vulnerability": 228,
      "spell_mana_tide_totem": 0,
      "spell_natures_swiftness": 0,
      "spell_natures_swiftnessd": 0,
      "spell_ancestral_spirit": 0,
      "spell_resurrection": 0,
      "spell_redemption": 0,
      "spell_rebirth": 0,
      "spell_bloodlust": 0,
      "spell_purge": 0,
      "spell_scroll_of_strength": 0,
      "spell_scroll_of_agility": 0,
      "spell_elixir_of_demonslaying": 0,
      "spell_braided_eternium_chain": 0,
      "spell_chain_of_the_twilight_owl": 0,
      "spell_eye_of_the_night": 1,
      "spell_dark_rune": 6,
      "spell_demonic_rune": 0,
      "spell_earth_shock": 0,
      "spell_earth_shock_r1": 0,
      "spell_kick": 0,
      "spell_counterspell": 0,
      "spell_drums_of_war": 0,
      "spell_drums_of_battle": 11,
      "spell_drums_of_speed": 0,
      "spell_drums_of_restoration": 0,
      "spell_nightmare_seed": 0,
      "spell_annihilator": 0,
      "spell_arcane_bomb": 0,
      "spell_fel_iron_bomb": 0,
      "spell_adamantite_grenade": 0,
      "spell_mass_dispel": 0,
      "spell_dispel_magic": 0,
      "spell_abolish_disease": 0,
      "spell_cleanse": 0,
      "spell_remove_lesser_curse": 0,
      "spell_spellsteal": 0,
      "spell_poison_cleansing_totem": 0,
      "spell_cure_poison": 0,
      "spell_cure_disease": 0,
      "spell_remove_curse": 0,
      "spell_abolish_poison": 0,
      "spell_shield_slam": 0,
      "spell_tranquilizing_shot": 0,
      "spell_commanding_shout": 0,
      "spell_battle_shout": 0,
      "spell_misdirection": 0,
      "mana_potion": 1
    },
    {
      "rank": 11,
      "name": "Skandalx",
      "total_damage": 5013693,
      "dps": 767.9,
      "useful_damage": 767.9,
      "total_heal": 67114,
      "hps": 10.2,
      "damage_taken": 0,
      "dtps": 0,
      "haste_potion": 13,
      "destruction_potion": 0,
      "goblin_sapper_charge": 2,
      "super_sapper_charge": 6,
      "spell_resurrects": 8,
      "spell_mark_of_the_wild": 0,
      "spell_faerie_fire": 0,
      "spell_fortitude": 0,
      "spell_intellect": 0,
      "spell_demonicdark_rune": 0,
      "spell_interrupts": 8,
      "spell_drums": 14,
      "spell_dispels": 9,
      "spell_shouts": 0,
      "spell_feladabomb": 0,
      "spell_gift_of_the_wild": 0,
      "spell_power_word:_fortitude": 0,
      "spell_prayer_of_fortitude": 0,
      "spell_arcane_intellect": 0,
      "spell_arcane_brilliance": 0,
      "spell_thunder_clap": 0,
      "spell_sunder_armor": 0,
      "spell_demoralizing_shout": 0,
      "spell_pummel": 0,
      "spell_faerie_fire_feral": 0,
      "spell_insect_swarm": 0,
      "spell_innervate": 0,
      "spell_curse_of_the_elements": 0,
      "spell_curse_of_recklessness": 0,
      "spell_curse_of_tongues": 0,
      "spell_curse_of_agony": 0,
      "spell_curse_of_doom": 0,
      "spell_shadow_vulnerability": 0,
      "spell_mana_tide_totem": 0,
      "spell_natures_swiftness": 0,
      "spell_natures_swiftnessd": 0,
      "spell_ancestral_spirit": 8,
      "spell_resurrection": 0,
      "spell_redemption": 0,
      "spell_rebirth": 0,
      "spell_bloodlust": 6,
      "spell_purge": 0,
      "spell_scroll_of_strength": 7,
      "spell_scroll_of_agility": 7,
      "spell_elixir_of_demonslaying": 6,
      "spell_braided_eternium_chain": 0,
      "spell_chain_of_the_twilight_owl": 0,
      "spell_eye_of_the_night": 0,
      "spell_dark_rune": 0,
      "spell_demonic_rune": 0,
      "spell_earth_shock": 8,
      "spell_earth_shock_r1": 0,
      "spell_kick": 0,
      "spell_counterspell": 0,
      "spell_drums_of_war": 0,
      "spell_drums_of_battle": 14,
      "spell_drums_of_speed": 0,
      "spell_drums_of_restoration": 0,
      "spell_nightmare_seed": 2,
      "spell_annihilator": 4,
      "spell_arcane_bomb": 0,
      "spell_fel_iron_bomb": 0,
      "spell_adamantite_grenade": 0,
      "spell_mass_dispel": 0,
      "spell_dispel_magic": 0,
      "spell_abolish_disease": 0,
      "spell_cleanse": 0,
      "spell_remove_lesser_curse": 0,
      "spell_spellsteal": 0,
      "spell_poison_cleansing_totem": 9,
      "spell_cure_poison": 0,
      "spell_cure_disease": 0,
      "spell_remove_curse": 0,
      "spell_abolish_poison": 0,
      "spell_shield_slam": 0,
      "spell_tranquilizing_shot": 0,
      "spell_commanding_shout": 0,
      "spell_battle_shout": 0,
      "spell_misdirection": 0,
      "mana_potion": 0
    },
    {
      "rank": 12,
      "name": "Egesham",
      "total_damage": 4926259,
      "dps": 754.5,
      "useful_damage": 754.5,
      "total_heal": 2496,
      "hps": 0.3,
      "damage_taken": 0,
      "dtps": 0,
      "haste_potion": 0,
      "destruction_potion": 12,
      "goblin_sapper_charge": 1,
      "super_sapper_charge": 1,
      "spell_resurrects": 3,
      "spell_mark_of_the_wild": 0,
      "spell_faerie_fire": 0,
      "spell_fortitude": 0,
      "spell_intellect": 0,
      "spell_demonicdark_rune": 5,
      "spell_interrupts": 12,
      "spell_drums": 15,
      "spell_dispels": 9,
      "spell_shouts": 0,
      "spell_feladabomb": 0,
      "spell_gift_of_the_wild": 0,
      "spell_power_word:_fortitude": 0,
      "spell_prayer_of_fortitude": 0,
      "spell_arcane_intellect": 0,
      "spell_arcane_brilliance": 0,
      "spell_thunder_clap": 0,
      "spell_sunder_armor": 0,
      "spell_demoralizing_shout": 0,
      "spell_pummel": 0,
      "spell_faerie_fire_feral": 0,
      "spell_insect_swarm": 0,
      "spell_innervate": 0,
      "spell_curse_of_the_elements": 0,
      "spell_curse_of_recklessness": 0,
      "spell_curse_of_tongues": 0,
      "spell_curse_of_agony": 0,
      "spell_curse_of_doom": 0,
      "spell_shadow_vulnerability": 0,
      "spell_mana_tide_totem": 0,
      "spell_natures_swiftness": 0,
      "spell_natures_swiftnessd": 0,
      "spell_ancestral_spirit": 3,
      "spell_resurrection": 0,
      "spell_redemption": 0,
      "spell_rebirth": 0,
      "spell_bloodlust": 6,
      "spell_purge": 1,
      "spell_scroll_of_strength": 0,
      "spell_scroll_of_agility": 0,
      "spell_elixir_of_demonslaying": 0,
      "spell_braided_eternium_chain": 0,
      "spell_chain_of_the_twilight_owl": 2,
      "spell_eye_of_the_night": 1,
      "spell_dark_rune": 5,
      "spell_demonic_rune": 0,
      "spell_earth_shock": 3,
      "spell_earth_shock_r1": 9,
      "spell_kick": 0,
      "spell_counterspell": 0,
      "spell_drums_of_war": 11,
      "spell_drums_of_battle": 4,
      "spell_drums_of_speed": 0,
      "spell_drums_of_restoration": 0,
      "spell_nightmare_seed": 2,
      "spell_annihilator": 0,
      "spell_arcane_bomb": 0,
      "spell_fel_iron_bomb": 0,
      "spell_adamantite_grenade": 0,
      "spell_mass_dispel": 0,
      "spell_dispel_magic": 0,
      "spell_abolish_disease": 0,
      "spell_cleanse": 0,
      "spell_remove_lesser_curse": 0,
      "spell_spellsteal": 0,
      "spell_poison_cleansing_totem": 8,
      "spell_cure_poison": 0,
      "spell_cure_disease": 0,
      "spell_remove_curse": 0,
      "spell_abolish_poison": 0,
      "spell_shield_slam": 0,
      "spell_tranquilizing_shot": 0,
      "spell_commanding_shout": 0,
      "spell_battle_shout": 0,
      "spell_misdirection": 0,
      "mana_potion": 8
    },
    {
      "rank": 13,
      "name": "Fenring",
      "total_damage": 4750880,
      "dps": 727.7,
      "useful_damage": 727.7,
      "total_heal": 62659,
      "hps": 9.5,
      "damage_taken": 0,
      "dtps": 0,
      "haste_potion": 11,
      "destruction_potion": 0,
      "goblin_sapper_charge": 0,
      "super_sapper_charge": 2,
      "spell_resurrects": 7,
      "spell_mark_of_the_wild": 0,
      "spell_faerie_fire": 0,
      "spell_fortitude": 0,
      "spell_intellect": 0,
      "spell_demonicdark_rune": 0,
      "spell_interrupts": 21,
      "spell_drums": 19,
      "spell_dispels": 15,
      "spell_shouts": 0,
      "spell_feladabomb": 0,
      "spell_gift_of_the_wild": 0,
      "spell_power_word:_fortitude": 0,
      "spell_prayer_of_fortitude": 0,
      "spell_arcane_intellect": 0,
      "spell_arcane_brilliance": 0,
      "spell_thunder_clap": 0,
      "spell_sunder_armor": 0,
      "spell_demoralizing_shout": 0,
      "spell_pummel": 0,
      "spell_faerie_fire_feral": 0,
      "spell_insect_swarm": 0,
      "spell_innervate": 0,
      "spell_curse_of_the_elements": 0,
      "spell_curse_of_recklessness": 0,
      "spell_curse_of_tongues": 0,
      "spell_curse_of_agony": 0,
      "spell_curse_of_doom": 0,
      "spell_shadow_vulnerability": 0,
      "spell_mana_tide_totem": 0,
      "spell_natures_swiftness": 0,
      "spell_natures_swiftnessd": 0,
      "spell_ancestral_spirit": 7,
      "spell_resurrection": 0,
      "spell_redemption": 0,
      "spell_rebirth": 0,
      "spell_bloodlust": 6,
      "spell_purge": 7,
      "spell_scroll_of_strength": 5,
      "spell_scroll_of_agility": 1,
      "spell_elixir_of_demonslaying": 5,
      "spell_braided_eternium_chain": 1,
      "spell_chain_of_the_twilight_owl": 0,
      "spell_eye_of_the_night": 0,
      "spell_dark_rune": 0,
      "spell_demonic_rune": 0,
      "spell_earth_shock": 21,
      "spell_earth_shock_r1": 0,
      "spell_kick": 0,
      "spell_counterspell": 0,
      "spell_drums_of_war": 0,
      "spell_drums_of_battle": 19,
      "spell_drums_of_speed": 0,
      "spell_drums_of_restoration": 0,
      "spell_nightmare_seed": 3,
      "spell_annihilator": 39,
      "spell_arcane_bomb": 0,
      "spell_fel_iron_bomb": 0,
      "spell_adamantite_grenade": 0,
      "spell_mass_dispel": 0,
      "spell_dispel_magic": 0,
      "spell_abolish_disease": 0,
      "spell_cleanse": 0,
      "spell_remove_lesser_curse": 0,
      "spell_spellsteal": 0,
      "spell_poison_cleansing_totem": 8,
      "spell_cure_poison": 0,
      "spell_cure_disease": 0,
      "spell_remove_curse": 0,
      "spell_abolish_poison": 0,
      "spell_shield_slam": 0,
      "spell_tranquilizing_shot": 0,
      "spell_commanding_shout": 0,
      "spell_battle_shout": 0,
      "spell_misdirection": 0,
      "mana_potion": 1
    },
    {
      "rank": 14,
      "name": "Richarddikk",
      "total_damage": 4749279,
      "dps": 727.4,
      "useful_damage": 727.4,
      "total_heal": 97205,
      "hps": 14.8,
      "damage_taken": 0,
      "dtps": 0,
      "haste_potion": 13,
      "destruction_potion": 0,
      "goblin_sapper_charge": 8,
      "super_sapper_charge": 1,
      "spell_resurrects": 0,
      "spell_mark_of_the_wild": 0,
      "spell_faerie_fire": 0,
      "spell_fortitude": 0,
      "spell_intellect": 0,
      "spell_demonicdark_rune": 1,
      "spell_interrupts": 4,
      "spell_drums": 15,
      "spell_dispels": 0,
      "spell_shouts": 0,
      "spell_feladabomb": 0,
      "spell_gift_of_the_wild": 0,
      "spell_power_word:_fortitude": 0,
      "spell_prayer_of_fortitude": 0,
      "spell_arcane_intellect": 0,
      "spell_arcane_brilliance": 0,
      "spell_thunder_clap": 0,
      "spell_sunder_armor": 0,
      "spell_demoralizing_shout": 0,
      "spell_pummel": 0,
      "spell_faerie_fire_feral": 0,
      "spell_insect_swarm": 0,
      "spell_innervate": 0,
      "spell_curse_of_the_elements": 0,
      "spell_curse_of_recklessness": 0,
      "spell_curse_of_tongues": 0,
      "spell_curse_of_agony": 0,
      "spell_curse_of_doom": 0,
      "spell_shadow_vulnerability": 0,
      "spell_mana_tide_totem": 0,
      "spell_natures_swiftness": 0,
      "spell_natures_swiftnessd": 0,
      "spell_ancestral_spirit": 0,
      "spell_resurrection": 0,
      "spell_redemption": 0,
      "spell_rebirth": 0,
      "spell_bloodlust": 0,
      "spell_purge": 0,
      "spell_scroll_of_strength": 4,
      "spell_scroll_of_agility": 4,
      "spell_elixir_of_demonslaying": 6,
      "spell_braided_eternium_chain": 2,
      "spell_chain_of_the_twilight_owl": 0,
      "spell_eye_of_the_night": 0,
      "spell_dark_rune": 0,
      "spell_demonic_rune": 1,
      "spell_earth_shock": 0,
      "spell_earth_shock_r1": 0,
      "spell_kick": 4,
      "spell_counterspell": 0,
      "spell_drums_of_war": 0,
      "spell_drums_of_battle": 15,
      "spell_drums_of_speed": 0,
      "spell_drums_of_restoration": 0,
      "spell_nightmare_seed": 0,
      "spell_annihilator": 0,
      "spell_arcane_bomb": 0,
      "spell_fel_iron_bomb": 0,
      "spell_adamantite_grenade": 0,
      "spell_mass_dispel": 0,
      "spell_dispel_magic": 0,
      "spell_abolish_disease": 0,
      "spell_cleanse": 0,
      "spell_remove_lesser_curse": 0,
      "spell_spellsteal": 0,
      "spell_poison_cleansing_totem": 0,
      "spell_cure_poison": 0,
      "spell_cure_disease": 0,
      "spell_remove_curse": 0,
      "spell_abolish_poison": 0,
      "spell_shield_slam": 0,
      "spell_tranquilizing_shot": 0,
      "spell_commanding_shout": 0,
      "spell_battle_shout": 0,
      "spell_misdirection": 0,
      "mana_potion": 0
    },
    {
      "rank": 15,
      "name": "Rkdd",
      "total_damage": 4265953,
      "dps": 653.4,
      "useful_damage": 653.4,
      "total_heal": 20723,
      "hps": 3.1,
      "damage_taken": 0,
      "dtps": 0,
      "haste_potion": 10,
      "destruction_potion": 0,
      "goblin_sapper_charge": 0,
      "super_sapper_charge": 0,
      "spell_resurrects": 0,
      "spell_mark_of_the_wild": 0,
      "spell_faerie_fire": 0,
      "spell_fortitude": 0,
      "spell_intellect": 0,
      "spell_demonicdark_rune": 0,
      "spell_interrupts": 0,
      "spell_drums": 12,
      "spell_dispels": 0,
      "spell_shouts": 0,
      "spell_feladabomb": 0,
      "spell_gift_of_the_wild": 0,
      "spell_power_word:_fortitude": 0,
      "spell_prayer_of_fortitude": 0,
      "spell_arcane_intellect": 0,
      "spell_arcane_brilliance": 0,
      "spell_thunder_clap": 0,
      "spell_sunder_armor": 0,
      "spell_demoralizing_shout": 0,
      "spell_pummel": 0,
      "spell_faerie_fire_feral": 0,
      "spell_insect_swarm": 0,
      "spell_innervate": 0,
      "spell_curse_of_the_elements": 0,
      "spell_curse_of_recklessness": 0,
      "spell_curse_of_tongues": 0,
      "spell_curse_of_agony": 0,
      "spell_curse_of_doom": 0,
      "spell_shadow_vulnerability": 0,
      "spell_mana_tide_totem": 0,
      "spell_natures_swiftness": 0,
      "spell_natures_swiftnessd": 0,
      "spell_ancestral_spirit": 0,
      "spell_resurrection": 0,
      "spell_redemption": 0,
      "spell_rebirth": 0,
      "spell_bloodlust": 0,
      "spell_purge": 0,
      "spell_scroll_of_strength": 6,
      "spell_scroll_of_agility": 5,
      "spell_elixir_of_demonslaying": 4,
      "spell_braided_eternium_chain": 0,
      "spell_chain_of_the_twilight_owl": 0,
      "spell_eye_of_the_night": 0,
      "spell_dark_rune": 0,
      "spell_demonic_rune": 0,
      "spell_earth_shock": 0,
      "spell_earth_shock_r1": 0,
      "spell_kick": 0,
      "spell_counterspell": 0,
      "spell_drums_of_war": 0,
      "spell_drums_of_battle": 12,
      "spell_drums_of_speed": 0,
      "spell_drums_of_restoration": 0,
      "spell_nightmare_seed": 2,
      "spell_annihilator": 0,
      "spell_arcane_bomb": 0,
      "spell_fel_iron_bomb": 0,
      "spell_adamantite_grenade": 0,
      "spell_mass_dispel": 0,
      "spell_dispel_magic": 0,
      "spell_abolish_disease": 0,
      "spell_cleanse": 0,
      "spell_remove_lesser_curse": 0,
      "spell_spellsteal": 0,
      "spell_poison_cleansing_totem": 0,
      "spell_cure_poison": 0,
      "spell_cure_disease": 0,
      "spell_remove_curse": 0,
      "spell_abolish_poison": 0,
      "spell_shield_slam": 0,
      "spell_tranquilizing_shot": 0,
      "spell_commanding_shout": 0,
      "spell_battle_shout": 0,
      "spell_misdirection": 14,
      "mana_potion": 2
    },
    {
      "rank": 16,
      "name": "Twisto",
      "total_damage": 4095410,
      "dps": 627.3,
      "useful_damage": 627.3,
      "total_heal": 69500,
      "hps": 10.6,
      "damage_taken": 0,
      "dtps": 0,
      "haste_potion": 7,
      "destruction_potion": 0,
      "goblin_sapper_charge": 3,
      "super_sapper_charge": 5,
      "spell_resurrects": 5,
      "spell_mark_of_the_wild": 0,
      "spell_faerie_fire": 0,
      "spell_fortitude": 0,
      "spell_intellect": 0,
      "spell_demonicdark_rune": 2,
      "spell_interrupts": 0,
      "spell_drums": 0,
      "spell_dispels": 10,
      "spell_shouts": 0,
      "spell_feladabomb": 3,
      "spell_gift_of_the_wild": 0,
      "spell_power_word:_fortitude": 0,
      "spell_prayer_of_fortitude": 0,
      "spell_arcane_intellect": 0,
      "spell_arcane_brilliance": 0,
      "spell_thunder_clap": 0,
      "spell_sunder_armor": 0,
      "spell_demoralizing_shout": 0,
      "spell_pummel": 0,
      "spell_faerie_fire_feral": 0,
      "spell_insect_swarm": 0,
      "spell_innervate": 0,
      "spell_curse_of_the_elements": 0,
      "spell_curse_of_recklessness": 0,
      "spell_curse_of_tongues": 0,
      "spell_curse_of_agony": 0,
      "spell_curse_of_doom": 0,
      "spell_shadow_vulnerability": 0,
      "spell_mana_tide_totem": 0,
      "spell_natures_swiftness": 0,
      "spell_natures_swiftnessd": 0,
      "spell_ancestral_spirit": 0,
      "spell_resurrection": 0,
      "spell_redemption": 5,
      "spell_rebirth": 0,
      "spell_bloodlust": 0,
      "spell_purge": 0,
      "spell_scroll_of_strength": 4,
      "spell_scroll_of_agility": 4,
      "spell_elixir_of_demonslaying": 4,
      "spell_braided_eternium_chain": 1,
      "spell_chain_of_the_twilight_owl": 0,
      "spell_eye_of_the_night": 0,
      "spell_dark_rune": 2,
      "spell_demonic_rune": 0,
      "spell_earth_shock": 0,
      "spell_earth_shock_r1": 0,
      "spell_kick": 0,
      "spell_counterspell": 0,
      "spell_drums_of_war": 0,
      "spell_drums_of_battle": 0,
      "spell_drums_of_speed": 0,
      "spell_drums_of_restoration": 0,
      "spell_nightmare_seed": 2,
      "spell_annihilator": 0,
      "spell_arcane_bomb": 0,
      "spell_fel_iron_bomb": 0,
      "spell_adamantite_grenade": 3,
      "spell_mass_dispel": 0,
      "spell_dispel_magic": 0,
      "spell_abolish_disease": 0,
      "spell_cleanse": 10,
      "spell_remove_lesser_curse": 0,
      "spell_spellsteal": 0,
      "spell_poison_cleansing_totem": 0,
      "spell_cure_poison": 0,
      "spell_cure_disease": 0,
      "spell_remove_curse": 0,
      "spell_abolish_poison": 0,
      "spell_shield_slam": 0,
      "spell_tranquilizing_shot": 0,
      "spell_commanding_shout": 0,
      "spell_battle_shout": 0,
      "spell_misdirection": 0,
      "mana_potion": 2
    },
    {
      "rank": 17,
      "name": "Dzowita",
      "total_damage": 3899817,
      "dps": 597.3,
      "useful_damage": 597.3,
      "total_heal": 4526,
      "hps": 0.6,
      "damage_taken": 0,
      "dtps": 0,
      "haste_potion": 0,
      "destruction_potion": 10,
      "goblin_sapper_charge": 0,
      "super_sapper_charge": 0,
      "spell_resurrects": 1,
      "spell_mark_of_the_wild": 78,
      "spell_faerie_fire": 53,
      "spell_fortitude": 0,
      "spell_intellect": 0,
      "spell_demonicdark_rune": 0,
      "spell_interrupts": 0,
      "spell_drums": 17,
      "spell_dispels": 40,
      "spell_shouts": 0,
      "spell_feladabomb": 0,
      "spell_gift_of_the_wild": 73,
      "spell_power_word:_fortitude": 0,
      "spell_prayer_of_fortitude": 0,
      "spell_arcane_intellect": 0,
      "spell_arcane_brilliance": 0,
      "spell_thunder_clap": 0,
      "spell_sunder_armor": 0,
      "spell_demoralizing_shout": 0,
      "spell_pummel": 0,
      "spell_faerie_fire_feral": 0,
      "spell_insect_swarm": 33,
      "spell_innervate": 7,
      "spell_curse_of_the_elements": 0,
      "spell_curse_of_recklessness": 0,
      "spell_curse_of_tongues": 0,
      "spell_curse_of_agony": 0,
      "spell_curse_of_doom": 0,
      "spell_shadow_vulnerability": 0,
      "spell_mana_tide_totem": 0,
      "spell_natures_swiftness": 0,
      "spell_natures_swiftnessd": 0,
      "spell_ancestral_spirit": 0,
      "spell_resurrection": 0,
      "spell_redemption": 0,
      "spell_rebirth": 1,
      "spell_bloodlust": 0,
      "spell_purge": 0,
      "spell_scroll_of_strength": 0,
      "spell_scroll_of_agility": 0,
      "spell_elixir_of_demonslaying": 0,
      "spell_braided_eternium_chain": 0,
      "spell_chain_of_the_twilight_owl": 1,
      "spell_eye_of_the_night": 2,
      "spell_dark_rune": 0,
      "spell_demonic_rune": 0,
      "spell_earth_shock": 0,
      "spell_earth_shock_r1": 0,
      "spell_kick": 0,
      "spell_counterspell": 0,
      "spell_drums_of_war": 2,
      "spell_drums_of_battle": 14,
      "spell_drums_of_speed": 0,
      "spell_drums_of_restoration": 1,
      "spell_nightmare_seed": 2,
      "spell_annihilator": 0,
      "spell_arcane_bomb": 0,
      "spell_fel_iron_bomb": 0,
      "spell_adamantite_grenade": 0,
      "spell_mass_dispel": 0,
      "spell_dispel_magic": 0,
      "spell_abolish_disease": 0,
      "spell_cleanse": 0,
      "spell_remove_lesser_curse": 0,
      "spell_spellsteal": 0,
      "spell_poison_cleansing_totem": 0,
      "spell_cure_poison": 0,
      "spell_cure_disease": 0,
      "spell_remove_curse": 40,
      "spell_abolish_poison": 0,
      "spell_shield_slam": 0,
      "spell_tranquilizing_shot": 0,
      "spell_commanding_shout": 0,
      "spell_battle_shout": 0,
      "spell_misdirection": 0,
      "mana_potion": 2
    },
    {
      "rank": 18,
      "name": "Holylolly",
      "total_damage": 3209281,
      "dps": 491.5,
      "useful_damage": 491.5,
      "total_heal": 693260,
      "hps": 106.1,
      "damage_taken": 0,
      "dtps": 0,
      "haste_potion": 0,
      "destruction_potion": 12,
      "goblin_sapper_charge": 0,
      "super_sapper_charge": 0,
      "spell_resurrects": 4,
      "spell_mark_of_the_wild": 0,
      "spell_faerie_fire": 0,
      "spell_fortitude": 99,
      "spell_intellect": 0,
      "spell_demonicdark_rune": 0,
      "spell_interrupts": 0,
      "spell_drums": 0,
      "spell_dispels": 32,
      "spell_shouts": 0,
      "spell_feladabomb": 0,
      "spell_gift_of_the_wild": 0,
      "spell_power_word:_fortitude": 10,
      "spell_prayer_of_fortitude": 89,
      "spell_arcane_intellect": 0,
      "spell_arcane_brilliance": 0,
      "spell_thunder_clap": 0,
      "spell_sunder_armor": 0,
      "spell_demoralizing_shout": 0,
      "spell_pummel": 0,
      "spell_faerie_fire_feral": 0,
      "spell_insect_swarm": 0,
      "spell_innervate": 0,
      "spell_curse_of_the_elements": 0,
      "spell_curse_of_recklessness": 0,
      "spell_curse_of_tongues": 0,
      "spell_curse_of_agony": 0,
      "spell_curse_of_doom": 0,
      "spell_shadow_vulnerability": 0,
      "spell_mana_tide_totem": 0,
      "spell_natures_swiftness": 0,
      "spell_natures_swiftnessd": 0,
      "spell_ancestral_spirit": 0,
      "spell_resurrection": 4,
      "spell_redemption": 0,
      "spell_rebirth": 0,
      "spell_bloodlust": 0,
      "spell_purge": 0,
      "spell_scroll_of_strength": 0,
      "spell_scroll_of_agility": 0,
      "spell_elixir_of_demonslaying": 0,
      "spell_braided_eternium_chain": 0,
      "spell_chain_of_the_twilight_owl": 2,
      "spell_eye_of_the_night": 1,
      "spell_dark_rune": 0,
      "spell_demonic_rune": 0,
      "spell_earth_shock": 0,
      "spell_earth_shock_r1": 0,
      "spell_kick": 0,
      "spell_counterspell": 0,
      "spell_drums_of_war": 0,
      "spell_drums_of_battle": 0,
      "spell_drums_of_speed": 0,
      "spell_drums_of_restoration": 0,
      "spell_nightmare_seed": 2,
      "spell_annihilator": 0,
      "spell_arcane_bomb": 0,
      "spell_fel_iron_bomb": 0,
      "spell_adamantite_grenade": 0,
      "spell_mass_dispel": 22,
      "spell_dispel_magic": 10,
      "spell_abolish_disease": 0,
      "spell_cleanse": 0,
      "spell_remove_lesser_curse": 0,
      "spell_spellsteal": 0,
      "spell_poison_cleansing_totem": 0,
      "spell_cure_poison": 0,
      "spell_cure_disease": 0,
      "spell_remove_curse": 0,
      "spell_abolish_poison": 0,
      "spell_shield_slam": 0,
      "spell_tranquilizing_shot": 0,
      "spell_commanding_shout": 0,
      "spell_battle_shout": 0,
      "spell_misdirection": 0,
      "mana_potion": 0
    },
    {
      "rank": 19,
      "name": "Mudley",
      "total_damage": 2705913,
      "dps": 414.4,
      "useful_damage": 414.4,
      "total_heal": 103670,
      "hps": 15.8,
      "damage_taken": 0,
      "dtps": 0,
      "haste_potion": 0,
      "destruction_potion": 0,
      "goblin_sapper_charge": 0,
      "super_sapper_charge": 0,
      "spell_resurrects": 1,
      "spell_mark_of_the_wild": 4,
      "spell_faerie_fire": 40,
      "spell_fortitude": 0,
      "spell_intellect": 0,
      "spell_demonicdark_rune": 0,
      "spell_interrupts": 0,
      "spell_drums": 6,
      "spell_dispels": 5,
      "spell_shouts": 0,
      "spell_feladabomb": 0,
      "spell_gift_of_the_wild": 0,
      "spell_power_word:_fortitude": 0,
      "spell_prayer_of_fortitude": 0,
      "spell_arcane_intellect": 0,
      "spell_arcane_brilliance": 0,
      "spell_thunder_clap": 0,
      "spell_sunder_armor": 0,
      "spell_demoralizing_shout": 0,
      "spell_pummel": 0,
      "spell_faerie_fire_feral": 40,
      "spell_insect_swarm": 0,
      "spell_innervate": 2,
      "spell_curse_of_the_elements": 0,
      "spell_curse_of_recklessness": 0,
      "spell_curse_of_tongues": 0,
      "spell_curse_of_agony": 0,
      "spell_curse_of_doom": 0,
      "spell_shadow_vulnerability": 0,
      "spell_mana_tide_totem": 0,
      "spell_natures_swiftness": 0,
      "spell_natures_swiftnessd": 0,
      "spell_ancestral_spirit": 0,
      "spell_resurrection": 0,
      "spell_redemption": 0,
      "spell_rebirth": 1,
      "spell_bloodlust": 0,
      "spell_purge": 0,
      "spell_scroll_of_strength": 0,
      "spell_scroll_of_agility": 0,
      "spell_elixir_of_demonslaying": 0,
      "spell_braided_eternium_chain": 0,
      "spell_chain_of_the_twilight_owl": 0,
      "spell_eye_of_the_night": 0,
      "spell_dark_rune": 0,
      "spell_demonic_rune": 0,
      "spell_earth_shock": 0,
      "spell_earth_shock_r1": 0,
      "spell_kick": 0,
      "spell_counterspell": 0,
      "spell_drums_of_war": 0,
      "spell_drums_of_battle": 6,
      "spell_drums_of_speed": 0,
      "spell_drums_of_restoration": 0,
      "spell_nightmare_seed": 6,
      "spell_annihilator": 0,
      "spell_arcane_bomb": 0,
      "spell_fel_iron_bomb": 0,
      "spell_adamantite_grenade": 0,
      "spell_mass_dispel": 0,
      "spell_dispel_magic": 0,
      "spell_abolish_disease": 0,
      "spell_cleanse": 0,
      "spell_remove_lesser_curse": 0,
      "spell_spellsteal": 0,
      "spell_poison_cleansing_totem": 0,
      "spell_cure_poison": 0,
      "spell_cure_disease": 0,
      "spell_remove_curse": 1,
      "spell_abolish_poison": 4,
      "spell_shield_slam": 0,
      "spell_tranquilizing_shot": 0,
      "spell_commanding_shout": 0,
      "spell_battle_shout": 0,
      "spell_misdirection": 0,
      "mana_potion": 1
    },
    {
      "rank": 20,
      "name": "Manbearduck",
      "total_damage": 2376465,
      "dps": 364.0,
      "useful_damage": 364.0,
      "total_heal": 102653,
      "hps": 15.7,
      "damage_taken": 0,
      "dtps": 0,
      "haste_potion": 0,
      "destruction_potion": 0,
      "goblin_sapper_charge": 0,
      "super_sapper_charge": 0,
      "spell_resurrects": 1,
      "spell_mark_of_the_wild": 0,
      "spell_faerie_fire": 28,
      "spell_fortitude": 0,
      "spell_intellect": 0,
      "spell_demonicdark_rune": 0,
      "spell_interrupts": 0,
      "spell_drums": 6,
      "spell_dispels": 0,
      "spell_shouts": 0,
      "spell_feladabomb": 0,
      "spell_gift_of_the_wild": 0,
      "spell_power_word:_fortitude": 0,
      "spell_prayer_of_fortitude": 0,
      "spell_arcane_intellect": 0,
      "spell_arcane_brilliance": 0,
      "spell_thunder_clap": 0,
      "spell_sunder_armor": 0,
      "spell_demoralizing_shout": 0,
      "spell_pummel": 0,
      "spell_faerie_fire_feral": 28,
      "spell_insect_swarm": 0,
      "spell_innervate": 1,
      "spell_curse_of_the_elements": 0,
      "spell_curse_of_recklessness": 0,
      "spell_curse_of_tongues": 0,
      "spell_curse_of_agony": 0,
      "spell_curse_of_doom": 0,
      "spell_shadow_vulnerability": 0,
      "spell_mana_tide_totem": 0,
      "spell_natures_swiftness": 0,
      "spell_natures_swiftnessd": 0,
      "spell_ancestral_spirit": 0,
      "spell_resurrection": 0,
      "spell_redemption": 0,
      "spell_rebirth": 1,
      "spell_bloodlust": 0,
      "spell_purge": 0,
      "spell_scroll_of_strength": 3,
      "spell_scroll_of_agility": 3,
      "spell_elixir_of_demonslaying": 1,
      "spell_braided_eternium_chain": 0,
      "spell_chain_of_the_twilight_owl": 0,
      "spell_eye_of_the_night": 0,
      "spell_dark_rune": 0,
      "spell_demonic_rune": 0,
      "spell_earth_shock": 0,
      "spell_earth_shock_r1": 0,
      "spell_kick": 0,
      "spell_counterspell": 0,
      "spell_drums_of_war": 0,
      "spell_drums_of_battle": 6,
      "spell_drums_of_speed": 0,
      "spell_drums_of_restoration": 0,
      "spell_nightmare_seed": 0,
      "spell_annihilator": 0,
      "spell_arcane_bomb": 0,
      "spell_fel_iron_bomb": 0,
      "spell_adamantite_grenade": 0,
      "spell_mass_dispel": 0,
      "spell_dispel_magic": 0,
      "spell_abolish_disease": 0,
      "spell_cleanse": 0,
      "spell_remove_lesser_curse": 0,
      "spell_spellsteal": 0,
      "spell_poison_cleansing_totem": 0,
      "spell_cure_poison": 0,
      "spell_cure_disease": 0,
      "spell_remove_curse": 0,
      "spell_abolish_poison": 0,
      "spell_shield_slam": 0,
      "spell_tranquilizing_shot": 0,
      "spell_commanding_shout": 0,
      "spell_battle_shout": 0,
      "spell_misdirection": 0,
      "mana_potion": 0
    },
    {
      "rank": 21,
      "name": "Kody",
      "total_damage": 1960372,
      "dps": 300.2,
      "useful_damage": 300.2,
      "total_heal": 263749,
      "hps": 40.3,
      "damage_taken": 0,
      "dtps": 0,
      "haste_potion": 0,
      "destruction_potion": 5,
      "goblin_sapper_charge": 0,
      "super_sapper_charge": 0,
      "spell_resurrects": 8,
      "spell_mark_of_the_wild": 0,
      "spell_faerie_fire": 0,
      "spell_fortitude": 0,
      "spell_intellect": 0,
      "spell_demonicdark_rune": 0,
      "spell_interrupts": 0,
      "spell_drums": 0,
      "spell_dispels": 7,
      "spell_shouts": 0,
      "spell_feladabomb": 7,
      "spell_gift_of_the_wild": 0,
      "spell_power_word:_fortitude": 0,
      "spell_prayer_of_fortitude": 0,
      "spell_arcane_intellect": 0,
      "spell_arcane_brilliance": 0,
      "spell_thunder_clap": 0,
      "spell_sunder_armor": 0,
      "spell_demoralizing_shout": 0,
      "spell_pummel": 0,
      "spell_faerie_fire_feral": 0,
      "spell_insect_swarm": 0,
      "spell_innervate": 0,
      "spell_curse_of_the_elements": 0,
      "spell_curse_of_recklessness": 0,
      "spell_curse_of_tongues": 0,
      "spell_curse_of_agony": 0,
      "spell_curse_of_doom": 0,
      "spell_shadow_vulnerability": 0,
      "spell_mana_tide_totem": 0,
      "spell_natures_swiftness": 0,
      "spell_natures_swiftnessd": 0,
      "spell_ancestral_spirit": 0,
      "spell_resurrection": 0,
      "spell_redemption": 8,
      "spell_rebirth": 0,
      "spell_bloodlust": 0,
      "spell_purge": 0,
      "spell_scroll_of_strength": 0,
      "spell_scroll_of_agility": 0,
      "spell_elixir_of_demonslaying": 0,
      "spell_braided_eternium_chain": 0,
      "spell_chain_of_the_twilight_owl": 0,
      "spell_eye_of_the_night": 0,
      "spell_dark_rune": 0,
      "spell_demonic_rune": 0,
      "spell_earth_shock": 0,
      "spell_earth_shock_r1": 0,
      "spell_kick": 0,
      "spell_counterspell": 0,
      "spell_drums_of_war": 0,
      "spell_drums_of_battle": 0,
      "spell_drums_of_speed": 0,
      "spell_drums_of_restoration": 0,
      "spell_nightmare_seed": 4,
      "spell_annihilator": 0,
      "spell_arcane_bomb": 0,
      "spell_fel_iron_bomb": 0,
      "spell_adamantite_grenade": 7,
      "spell_mass_dispel": 0,
      "spell_dispel_magic": 0,
      "spell_abolish_disease": 0,
      "spell_cleanse": 7,
      "spell_remove_lesser_curse": 0,
      "spell_spellsteal": 0,
      "spell_poison_cleansing_totem": 0,
      "spell_cure_poison": 0,
      "spell_cure_disease": 0,
      "spell_remove_curse": 0,
      "spell_abolish_poison": 0,
      "spell_shield_slam": 0,
      "spell_tranquilizing_shot": 0,
      "spell_commanding_shout": 0,
      "spell_battle_shout": 0,
      "spell_misdirection": 0,
      "mana_potion": 5
    },
    {
      "rank": 22,
      "name": "Monkeyslut",
      "total_damage": 107176,
      "dps": 16.4,
      "useful_damage": 16.4,
      "total_heal": 3476026,
      "hps": 532.4,
      "damage_taken": 0,
      "dtps": 0,
      "haste_potion": 0,
      "destruction_potion": 0,
      "goblin_sapper_charge": 0,
      "super_sapper_charge": 0,
      "spell_resurrects": 6,
      "spell_mark_of_the_wild": 0,
      "spell_faerie_fire": 0,
      "spell_fortitude": 0,
      "spell_intellect": 0,
      "spell_demonicdark_rune": 0,
      "spell_interrupts": 0,
      "spell_drums": 9,
      "spell_dispels": 26,
      "spell_shouts": 0,
      "spell_feladabomb": 0,
      "spell_gift_of_the_wild": 0,
      "spell_power_word:_fortitude": 0,
      "spell_prayer_of_fortitude": 0,
      "spell_arcane_intellect": 0,
      "spell_arcane_brilliance": 0,
      "spell_thunder_clap": 0,
      "spell_sunder_armor": 0,
      "spell_demoralizing_shout": 0,
      "spell_pummel": 0,
      "spell_faerie_fire_feral": 0,
      "spell_insect_swarm": 0,
      "spell_innervate": 0,
      "spell_curse_of_the_elements": 0,
      "spell_curse_of_recklessness": 0,
      "spell_curse_of_tongues": 0,
      "spell_curse_of_agony": 0,
      "spell_curse_of_doom": 0,
      "spell_shadow_vulnerability": 0,
      "spell_mana_tide_totem": 0,
      "spell_natures_swiftness": 4,
      "spell_natures_swiftnessd": 0,
      "spell_ancestral_spirit": 6,
      "spell_resurrection": 0,
      "spell_redemption": 0,
      "spell_rebirth": 0,
      "spell_bloodlust": 5,
      "spell_purge": 0,
      "spell_scroll_of_strength": 0,
      "spell_scroll_of_agility": 0,
      "spell_elixir_of_demonslaying": 0,
      "spell_braided_eternium_chain": 0,
      "spell_chain_of_the_twilight_owl": 0,
      "spell_eye_of_the_night": 0,
      "spell_dark_rune": 0,
      "spell_demonic_rune": 0,
      "spell_earth_shock": 0,
      "spell_earth_shock_r1": 0,
      "spell_kick": 0,
      "spell_counterspell": 0,
      "spell_drums_of_war": 0,
      "spell_drums_of_battle": 9,
      "spell_drums_of_speed": 0,
      "spell_drums_of_restoration": 0,
      "spell_nightmare_seed": 2,
      "spell_annihilator": 0,
      "spell_arcane_bomb": 0,
      "spell_fel_iron_bomb": 0,
      "spell_adamantite_grenade": 0,
      "spell_mass_dispel": 0,
      "spell_dispel_magic": 0,
      "spell_abolish_disease": 0,
      "spell_cleanse": 0,
      "spell_remove_lesser_curse": 0,
      "spell_spellsteal": 0,
      "spell_poison_cleansing_totem": 8,
      "spell_cure_poison": 18,
      "spell_cure_disease": 0,
      "spell_remove_curse": 0,
      "spell_abolish_poison": 0,
      "spell_shield_slam": 0,
      "spell_tranquilizing_shot": 0,
      "spell_commanding_shout": 0,
      "spell_battle_shout": 0,
      "spell_misdirection": 0,
      "mana_potion": 0
    },
    {
      "rank": 23,
      "name": "Karirunk",
      "total_damage": 103509,
      "dps": 15.8,
      "useful_damage": 15.8,
      "total_heal": 3408239,
      "hps": 522.0,
      "damage_taken": 0,
      "dtps": 0,
      "haste_potion": 0,
      "destruction_potion": 0,
      "goblin_sapper_charge": 0,
      "super_sapper_charge": 0,
      "spell_resurrects": 4,
      "spell_mark_of_the_wild": 0,
      "spell_faerie_fire": 0,
      "spell_fortitude": 0,
      "spell_intellect": 0,
      "spell_demonicdark_rune": 0,
      "spell_interrupts": 5,
      "spell_drums": 17,
      "spell_dispels": 46,
      "spell_shouts": 0,
      "spell_feladabomb": 0,
      "spell_gift_of_the_wild": 0,
      "spell_power_word:_fortitude": 0,
      "spell_prayer_of_fortitude": 0,
      "spell_arcane_intellect": 0,
      "spell_arcane_brilliance": 0,
      "spell_thunder_clap": 0,
      "spell_sunder_armor": 0,
      "spell_demoralizing_shout": 0,
      "spell_pummel": 0,
      "spell_faerie_fire_feral": 0,
      "spell_insect_swarm": 0,
      "spell_innervate": 0,
      "spell_curse_of_the_elements": 0,
      "spell_curse_of_recklessness": 0,
      "spell_curse_of_tongues": 0,
      "spell_curse_of_agony": 0,
      "spell_curse_of_doom": 0,
      "spell_shadow_vulnerability": 0,
      "spell_mana_tide_totem": 10,
      "spell_natures_swiftness": 9,
      "spell_natures_swiftnessd": 0,
      "spell_ancestral_spirit": 4,
      "spell_resurrection": 0,
      "spell_redemption": 0,
      "spell_rebirth": 0,
      "spell_bloodlust": 5,
      "spell_purge": 0,
      "spell_scroll_of_strength": 0,
      "spell_scroll_of_agility": 0,
      "spell_elixir_of_demonslaying": 0,
      "spell_braided_eternium_chain": 0,
      "spell_chain_of_the_twilight_owl": 0,
      "spell_eye_of_the_night": 0,
      "spell_dark_rune": 0,
      "spell_demonic_rune": 0,
      "spell_earth_shock": 0,
      "spell_earth_shock_r1": 5,
      "spell_kick": 0,
      "spell_counterspell": 0,
      "spell_drums_of_war": 0,
      "spell_drums_of_battle": 1,
      "spell_drums_of_speed": 0,
      "spell_drums_of_restoration": 16,
      "spell_nightmare_seed": 2,
      "spell_annihilator": 0,
      "spell_arcane_bomb": 0,
      "spell_fel_iron_bomb": 0,
      "spell_adamantite_grenade": 0,
      "spell_mass_dispel": 0,
      "spell_dispel_magic": 0,
      "spell_abolish_disease": 0,
      "spell_cleanse": 0,
      "spell_remove_lesser_curse": 0,
      "spell_spellsteal": 0,
      "spell_poison_cleansing_totem": 9,
      "spell_cure_poison": 37,
      "spell_cure_disease": 0,
      "spell_remove_curse": 0,
      "spell_abolish_poison": 0,
      "spell_shield_slam": 0,
      "spell_tranquilizing_shot": 0,
      "spell_commanding_shout": 0,
      "spell_battle_shout": 0,
      "spell_misdirection": 0,
      "mana_potion": 4
    },
    {
      "rank": 24,
      "name": "Elylea",
      "total_damage": 47501,
      "dps": 7.2,
      "useful_damage": 7.2,
      "total_heal": 1110994,
      "hps": 170.1,
      "damage_taken": 0,
      "dtps": 0,
      "haste_potion": 0,
      "destruction_potion": 0,
      "goblin_sapper_charge": 0,
      "super_sapper_charge": 0,
      "spell_resurrects": 6,
      "spell_mark_of_the_wild": 0,
      "spell_faerie_fire": 0,
      "spell_fortitude": 0,
      "spell_intellect": 0,
      "spell_demonicdark_rune": 1,
      "spell_interrupts": 0,
      "spell_drums": 0,
      "spell_dispels": 46,
      "spell_shouts": 0,
      "spell_feladabomb": 0,
      "spell_gift_of_the_wild": 0,
      "spell_power_word:_fortitude": 0,
      "spell_prayer_of_fortitude": 0,
      "spell_arcane_intellect": 0,
      "spell_arcane_brilliance": 0,
      "spell_thunder_clap": 0,
      "spell_sunder_armor": 0,
      "spell_demoralizing_shout": 0,
      "spell_pummel": 0,
      "spell_faerie_fire_feral": 0,
      "spell_insect_swarm": 0,
      "spell_innervate": 0,
      "spell_curse_of_the_elements": 0,
      "spell_curse_of_recklessness": 0,
      "spell_curse_of_tongues": 0,
      "spell_curse_of_agony": 0,
      "spell_curse_of_doom": 0,
      "spell_shadow_vulnerability": 0,
      "spell_mana_tide_totem": 0,
      "spell_natures_swiftness": 0,
      "spell_natures_swiftnessd": 0,
      "spell_ancestral_spirit": 0,
      "spell_resurrection": 0,
      "spell_redemption": 6,
      "spell_rebirth": 0,
      "spell_bloodlust": 0,
      "spell_purge": 0,
      "spell_scroll_of_strength": 0,
      "spell_scroll_of_agility": 0,
      "spell_elixir_of_demonslaying": 0,
      "spell_braided_eternium_chain": 0,
      "spell_chain_of_the_twilight_owl": 0,
      "spell_eye_of_the_night": 0,
      "spell_dark_rune": 1,
      "spell_demonic_rune": 0,
      "spell_earth_shock": 0,
      "spell_earth_shock_r1": 0,
      "spell_kick": 0,
      "spell_counterspell": 0,
      "spell_drums_of_war": 0,
      "spell_drums_of_battle": 0,
      "spell_drums_of_speed": 0,
      "spell_drums_of_restoration": 0,
      "spell_nightmare_seed": 1,
      "spell_annihilator": 0,
      "spell_arcane_bomb": 0,
      "spell_fel_iron_bomb": 0,
      "spell_adamantite_grenade": 0,
      "spell_mass_dispel": 0,
      "spell_dispel_magic": 0,
      "spell_abolish_disease": 0,
      "spell_cleanse": 46,
      "spell_remove_lesser_curse": 0,
      "spell_spellsteal": 0,
      "spell_poison_cleansing_totem": 0,
      "spell_cure_poison": 0,
      "spell_cure_disease": 0,
      "spell_remove_curse": 0,
      "spell_abolish_poison": 0,
      "spell_shield_slam": 0,
      "spell_tranquilizing_shot": 0,
      "spell_commanding_shout": 0,
      "spell_battle_shout": 0,
      "spell_misdirection": 0,
      "mana_potion": 3
    },
    {
      "rank": 25,
      "name": "Finality",
      "total_damage": 28883,
      "dps": 4.4,
      "useful_damage": 4.4,
      "total_heal": 3460635,
      "hps": 530.0,
      "damage_taken": 0,
      "dtps": 0,
      "haste_potion": 0,
      "destruction_potion": 0,
      "goblin_sapper_charge": 0,
      "super_sapper_charge": 0,
      "spell_resurrects": 9,
      "spell_mark_of_the_wild": 0,
      "spell_faerie_fire": 0,
      "spell_fortitude": 37,
      "spell_intellect": 0,
      "spell_demonicdark_rune": 1,
      "spell_interrupts": 0,
      "spell_drums": 0,
      "spell_dispels": 88,
      "spell_shouts": 0,
      "spell_feladabomb": 0,
      "spell_gift_of_the_wild": 0,
      "spell_power_word:_fortitude": 10,
      "spell_prayer_of_fortitude": 27,
      "spell_arcane_intellect": 0,
      "spell_arcane_brilliance": 0,
      "spell_thunder_clap": 0,
      "spell_sunder_armor": 0,
      "spell_demoralizing_shout": 0,
      "spell_pummel": 0,
      "spell_faerie_fire_feral": 0,
      "spell_insect_swarm": 0,
      "spell_innervate": 0,
      "spell_curse_of_the_elements": 0,
      "spell_curse_of_recklessness": 0,
      "spell_curse_of_tongues": 0,
      "spell_curse_of_agony": 0,
      "spell_curse_of_doom": 0,
      "spell_shadow_vulnerability": 0,
      "spell_mana_tide_totem": 0,
      "spell_natures_swiftness": 0,
      "spell_natures_swiftnessd": 0,
      "spell_ancestral_spirit": 0,
      "spell_resurrection": 9,
      "spell_redemption": 0,
      "spell_rebirth": 0,
      "spell_bloodlust": 0,
      "spell_purge": 0,
      "spell_scroll_of_strength": 0,
      "spell_scroll_of_agility": 0,
      "spell_elixir_of_demonslaying": 0,
      "spell_braided_eternium_chain": 0,
      "spell_chain_of_the_twilight_owl": 0,
      "spell_eye_of_the_night": 0,
      "spell_dark_rune": 1,
      "spell_demonic_rune": 0,
      "spell_earth_shock": 0,
      "spell_earth_shock_r1": 0,
      "spell_kick": 0,
      "spell_counterspell": 0,
      "spell_drums_of_war": 0,
      "spell_drums_of_battle": 0,
      "spell_drums_of_speed": 0,
      "spell_drums_of_restoration": 0,
      "spell_nightmare_seed": 0,
      "spell_annihilator": 0,
      "spell_arcane_bomb": 0,
      "spell_fel_iron_bomb": 0,
      "spell_adamantite_grenade": 0,
      "spell_mass_dispel": 51,
      "spell_dispel_magic": 36,
      "spell_abolish_disease": 1,
      "spell_cleanse": 0,
      "spell_remove_lesser_curse": 0,
      "spell_spellsteal": 0,
      "spell_poison_cleansing_totem": 0,
      "spell_cure_poison": 0,
      "spell_cure_disease": 0,
      "spell_remove_curse": 0,
      "spell_abolish_poison": 0,
      "spell_shield_slam": 0,
      "spell_tranquilizing_shot": 0,
      "spell_commanding_shout": 0,
      "spell_battle_shout": 0,
      "spell_misdirection": 0,
      "mana_potion": 4
    },
    {
      "rank": 26,
      "name": "Onionring",
      "total_damage": 25947,
      "dps": 3.9,
      "useful_damage": 3.9,
      "total_heal": 3646768,
      "hps": 558.5,
      "damage_taken": 0,
      "dtps": 0,
      "haste_potion": 0,
      "destruction_potion": 0,
      "goblin_sapper_charge": 0,
      "super_sapper_charge": 0,
      "spell_resurrects": 1,
      "spell_mark_of_the_wild": 78,
      "spell_faerie_fire": 0,
      "spell_fortitude": 0,
      "spell_intellect": 0,
      "spell_demonicdark_rune": 0,
      "spell_interrupts": 0,
      "spell_drums": 0,
      "spell_dispels": 14,
      "spell_shouts": 0,
      "spell_feladabomb": 0,
      "spell_gift_of_the_wild": 57,
      "spell_power_word:_fortitude": 0,
      "spell_prayer_of_fortitude": 0,
      "spell_arcane_intellect": 0,
      "spell_arcane_brilliance": 0,
      "spell_thunder_clap": 0,
      "spell_sunder_armor": 0,
      "spell_demoralizing_shout": 0,
      "spell_pummel": 0,
      "spell_faerie_fire_feral": 0,
      "spell_insect_swarm": 0,
      "spell_innervate": 3,
      "spell_curse_of_the_elements": 0,
      "spell_curse_of_recklessness": 0,
      "spell_curse_of_tongues": 0,
      "spell_curse_of_agony": 0,
      "spell_curse_of_doom": 0,
      "spell_shadow_vulnerability": 0,
      "spell_mana_tide_totem": 0,
      "spell_natures_swiftness": 0,
      "spell_natures_swiftnessd": 1,
      "spell_ancestral_spirit": 0,
      "spell_resurrection": 0,
      "spell_redemption": 0,
      "spell_rebirth": 1,
      "spell_bloodlust": 0,
      "spell_purge": 0,
      "spell_scroll_of_strength": 0,
      "spell_scroll_of_agility": 0,
      "spell_elixir_of_demonslaying": 0,
      "spell_braided_eternium_chain": 0,
      "spell_chain_of_the_twilight_owl": 0,
      "spell_eye_of_the_night": 0,
      "spell_dark_rune": 0,
      "spell_demonic_rune": 0,
      "spell_earth_shock": 0,
      "spell_earth_shock_r1": 0,
      "spell_kick": 0,
      "spell_counterspell": 0,
      "spell_drums_of_war": 0,
      "spell_drums_of_battle": 0,
      "spell_drums_of_speed": 0,
      "spell_drums_of_restoration": 0,
      "spell_nightmare_seed": 0,
      "spell_annihilator": 0,
      "spell_arcane_bomb": 0,
      "spell_fel_iron_bomb": 0,
      "spell_adamantite_grenade": 0,
      "spell_mass_dispel": 0,
      "spell_dispel_magic": 0,
      "spell_abolish_disease": 0,
      "spell_cleanse": 0,
      "spell_remove_lesser_curse": 0,
      "spell_spellsteal": 0,
      "spell_poison_cleansing_totem": 0,
      "spell_cure_poison": 0,
      "spell_cure_disease": 0,
      "spell_remove_curse": 12,
      "spell_abolish_poison": 2,
      "spell_shield_slam": 0,
      "spell_tranquilizing_shot": 0,
      "spell_commanding_shout": 0,
      "spell_battle_shout": 0,
      "spell_misdirection": 0,
      "mana_potion": 2
    }
  ],
  "total_players": 26
}